pyw/__init__.py
pyw/motion/__init__.py
pyw_motion-0.0.0.post2.dist-info/METADATA
pyw_motion-0.0.0.post2.dist-info/WHEEL
pyw_motion-0.0.0.post2.dist-info/licenses/LICENSE
pyw_motion-0.0.0.post2.dist-info/RECORD
