Metadata-Version: 2.4
Name: pyw-motion
Version: 0.0.0.post2
Summary: Reserved placeholder for pyw-motion (motion-detection helpers)
Project-URL: Homepage, https://github.com/pythonWoods/pyw-motion
Project-URL: Documentation, https://pythonwoods.dev/docs/pyw-motion/latest/
Project-URL: Issues, https://github.com/pythonWoods/pyw-motion/issues
Project-URL: Changelog, https://github.com/pythonWoods/pyw-motion/releases
Author: pythonWoods
License: MIT
License-File: LICENSE
Classifier: Development Status :: 2 - Pre-Alpha
Classifier: License :: OSI Approved :: MIT License
Classifier: Programming Language :: Python :: 3 :: Only
Classifier: Programming Language :: Python :: 3.11
Classifier: Typing :: Typed
Requires-Python: >=3.9
Requires-Dist: pyw-core>=0.0.0
